sphinxcontrib/__init__.py
sphinxcontrib/cairosvgconverter.py
sphinxcontrib/inkscapeconverter.py
sphinxcontrib/rsvgconverter.py
sphinxcontrib_svg2pdfconverter-1.3.0.dist-info/LICENSE.txt
sphinxcontrib_svg2pdfconverter-1.3.0.dist-info/METADATA
sphinxcontrib_svg2pdfconverter-1.3.0.dist-info/WHEEL
sphinxcontrib_svg2pdfconverter-1.3.0.dist-info/top_level.txt
sphinxcontrib_svg2pdfconverter-1.3.0.dist-info/RECORD
