Metadata-Version: 2.2
Name: sphinxcontrib-svg2pdfconverter
Version: 1.3.0
Summary: Sphinx SVG to PDF converter extension
Author-email: Stefan Wiehler <sphinx_contribute@missinglinkelectronics.com>
License: BSD-2-Clause
Project-URL: Homepage, https://github.com/missinglinkelectronics/sphinxcontrib-svg2pdfconverter
Project-URL: Download, https://pypi.org/project/sphinxcontrib-svg2pdfconverter
Classifier: Development Status :: 5 - Production/Stable
Classifier: Environment :: Console
Classifier: Environment :: Web Environment
Classifier: Framework :: Sphinx :: Extension
Classifier: Intended Audience :: Developers
Classifier: License :: OSI Approved :: BSD License
Classifier: Operating System :: OS Independent
Classifier: Programming Language :: Python :: 3
Classifier: Topic :: Documentation
Classifier: Topic :: Utilities
Requires-Python: >=3.6
License-File: LICENSE.txt
Requires-Dist: Sphinx>=1.6.3
Provides-Extra: cairosvg
Requires-Dist: cairosvg>=1.0; extra == "cairosvg"
